README.rst
setup.py
datestr/__init__.py
datestr.egg-info/PKG-INFO
datestr.egg-info/SOURCES.txt
datestr.egg-info/dependency_links.txt
datestr.egg-info/not-zip-safe
datestr.egg-info/requires.txt
datestr.egg-info/top_level.txt