Metadata-Version: 1.1
Name: datestr
Version: 0.1.0
Summary: Wrapper object around relativedelta to manage date and datetime strings
Home-page: https://github.com/chermed/datestr
Author: Mohamed Cherkaoui
Author-email: chermed@gmail.com
License: GNU General Public License v3
Keywords: datestr date datetime odoo string convert
Platform: UNKNOWN
Classifier: Development Status :: 2 - Pre-Alpha
Classifier: Intended Audience :: Developers
Classifier: License :: OSI Approved :: GNU General Public License v3 (GPLv3)
Classifier: Natural Language :: English
Classifier: Programming Language :: Python :: 2
Classifier: Programming Language :: Python :: 2.6
Classifier: Programming Language :: Python :: 2.7
Classifier: Programming Language :: Python :: 3
Classifier: Programming Language :: Python :: 3.3
Classifier: Programming Language :: Python :: 3.4
Classifier: Programming Language :: Python :: 3.5
